src/__init__.py
src/cli/__init__.py
src/cli/cliRunner.py
src/cli/utils.py
src/cli/commands/__init__.py
src/cli/commands/parse_analysis/__init__.py
src/cli/commands/parse_analysis/parse_analysis.py
src/cli/commands/parse_analysis/results.py
src/cli/commands/parse_available/__init__.py
src/cli/commands/parse_available/parse_available.py
src/cli/commands/parse_calculate/__init__.py
src/cli/commands/parse_calculate/parse_calculate.py
src/cli/commands/parse_calculate/utils.py
src/cli/commands/parse_change_name/__init__.py
src/cli/commands/parse_change_name/parse_change_name.py
src/cli/commands/parse_create/__init__.py
src/cli/commands/parse_create/parse_create.py
src/cli/commands/parse_create/utils.py
src/cli/commands/parse_generate/__init__.py
src/cli/commands/parse_generate/generate_utils.py
src/cli/commands/parse_generate/parse_generate.py
src/cli/commands/parse_get_entity/__init__.py
src/cli/commands/parse_get_entity/parse_get_entity.py
src/cli/commands/parse_get_entity/utils.py
src/cli/commands/parse_import/__init__.py
src/cli/commands/parse_import/parse_import.py
src/cli/commands/parse_init/__init__.py
src/cli/commands/parse_init/parse_init.py
src/cli/commands/parse_init/utils.py
src/cli/commands/parse_list/__init__.py
src/cli/commands/parse_list/parse_list.py
src/cli/commands/parse_show/__init__.py
src/cli/commands/parse_show/parse_show.py
src/cli/exceptions/__init__.py
src/cli/exceptions/exceptions.py
src/cli/jsonReader/__init__.py
src/cli/jsonReader/jsonReader.py
src/clients/__init__.py
src/clients/service_client.py
src/config/__init__.py
src/config/settings.py
tests/__init__.py
tests/test_helpers.py
tests/integration/__init__.py
tests/system/__init__.py
tests/system/test_analysis.py
tests/system/test_available.py
tests/system/test_change_name.py
tests/system/test_help.py
tests/system/test_import.py
tests/system/test_list.py
tests/system/test_no_env.py
tests/system/test_show.py
tests/system/test_sigint.py
tests/unit/__init__.py
tests/unit/test_available.py
measuresoftgram-3.4.6.dist-info/LICENSE
measuresoftgram-3.4.6.dist-info/METADATA
measuresoftgram-3.4.6.dist-info/WHEEL
measuresoftgram-3.4.6.dist-info/entry_points.txt
measuresoftgram-3.4.6.dist-info/top_level.txt
measuresoftgram-3.4.6.dist-info/RECORD
